{
    "title": "Чехия",
    "description": "Короткое описание страны",
    "attractiont": [
        {
            "name": "Карлов мост",
            "description": "Описание достопримечательности Карлов мост"
        },
        {
            "name": "Собор Святого Вита",
            "description": "Описание достопримечательности Собор Святого Вита"
        },
        {
            "name": "Пражские куранты",
            "description": "Описание достопримечательности Пражские куранты"
        }
    ]
}